unrasterize/__init__.py
unrasterize/classes.py
unrasterize-1.0.0.dist-info/DESCRIPTION.rst
unrasterize-1.0.0.dist-info/METADATA
unrasterize-1.0.0.dist-info/RECORD
unrasterize-1.0.0.dist-info/WHEEL
unrasterize-1.0.0.dist-info/metadata.json
unrasterize-1.0.0.dist-info/top_level.txt
