Metadata-Version: 2.0
Name: unrasterize
Version: 1.0.0
Summary: A simple API for lossfully converting raster datasets to GeoJSON.
Home-page: http://github.com/tetraptych/unrasterize
Author: Brian Lewis
Author-email: brianburkelewis@gmail.com
License: MIT
Keywords: geospatial,geo,raster,gdal
Platform: UNKNOWN
Classifier: Intended Audience :: Developers
Classifier: Intended Audience :: Information Technology
Classifier: Intended Audience :: Science/Research
Classifier: Programming Language :: Python :: 3.6
Classifier: Topic :: Scientific/Engineering :: GIS
Requires-Python: >=3
Requires-Dist: rasterio (>=1.0a12)
Requires-Dist: pathos (>=0.2.0)
Requires-Dist: numpy (>=1.8.0)
Requires-Dist: geojson (>=1.3.0)
Requires-Dist: geopandas (>=0.2.0)
